clientpkgs/__init__.py
clientpkgs/accounts_billing.py
clientpkgs/accounts_client.py
clientpkgs/accounts_iam.py
clientpkgs/accounts_oauth.py
clientpkgs/accounts_provisioning_client.py
clientpkgs/accounts_settings.py
clientpkgs/accounts_uc_client.py
clientpkgs/apps_client.py
clientpkgs/azure_accounts_client.py
clientpkgs/cleanrooms_client.py
clientpkgs/clusters_client.py
clientpkgs/dbfs_client.py
clientpkgs/dbsql_client.py
clientpkgs/delta_sharing.py
clientpkgs/init_scripts_client.py
clientpkgs/ip_access_list.py
clientpkgs/job_runs_client.py
clientpkgs/jobs_client.py
clientpkgs/lakeview_client.py
clientpkgs/libraries_client.py
clientpkgs/managed_libraries_client.py
clientpkgs/marketplace_client.py
clientpkgs/ml_flow_client.py
clientpkgs/notifications_destination.py
clientpkgs/permissions_client.py
clientpkgs/pipelines_client.py
clientpkgs/policies_client.py
clientpkgs/pools_client.py
clientpkgs/qualitymonitors_client.py
clientpkgs/repos_client.py
clientpkgs/scim_client.py
clientpkgs/secrets_client.py
clientpkgs/serving_endpoints.py
clientpkgs/tokens_client.py
clientpkgs/unity_catalog_client.py
clientpkgs/vector_search.py
clientpkgs/workspace_client.py
clientpkgs/ws_settings_client.py
core/__init__.py
core/dbclient.py
core/logging_utils.py
core/parser.py
core/wmconstants.py
dbl_sat_sdk-0.1.38.dist-info/licenses/LICENSE
dbl_sat_sdk-0.1.38.dist-info/METADATA
dbl_sat_sdk-0.1.38.dist-info/WHEEL
dbl_sat_sdk-0.1.38.dist-info/top_level.txt
dbl_sat_sdk-0.1.38.dist-info/RECORD
