Metadata-Version: 2.4
Name: dbl-sat-sdk
Version: 0.1.38
Summary: Databricks Security Analysis Tool
Home-page: https://databricks.com/learn/labs
Author: Arun Pamulapati, Anindita Mahapatra, Ram Murali
Author-email: sat@databricks.com
Classifier: Programming Language :: Python :: 3
Classifier: License :: Other/Proprietary License
Classifier: Operating System :: OS Independent
Requires-Python: >=3.8
License-File: LICENSE
Requires-Dist: requests
Requires-Dist: msal
Dynamic: author
Dynamic: author-email
Dynamic: classifier
Dynamic: description
Dynamic: description-content-type
Dynamic: home-page
Dynamic: license-file
Dynamic: requires-dist
Dynamic: requires-python
Dynamic: summary
